server.py
math_server-0.1.1.dist-info/METADATA
math_server-0.1.1.dist-info/WHEEL
math_server-0.1.1.dist-info/entry_points.txt
math_server-0.1.1.dist-info/top_level.txt
math_server-0.1.1.dist-info/RECORD
