Metadata-Version: 2.4
Name: math-server
Version: 0.1.1
Summary: Add your description here
Requires-Python: >=3.13
Requires-Dist: fastapi>=0.117.1
Requires-Dist: mcp>=1.15.0
Requires-Dist: uvicorn>=0.37.0
